iparcelboxpy/__init__.py
iParcelBoxPy-0.0.1.dist-info/LICENSE.txt
iParcelBoxPy-0.0.1.dist-info/METADATA
iParcelBoxPy-0.0.1.dist-info/WHEEL
iParcelBoxPy-0.0.1.dist-info/top_level.txt
iParcelBoxPy-0.0.1.dist-info/RECORD
