Metadata-Version: 2.1
Name: iParcelBoxPy
Version: 0.0.1
Summary: Python wrapper for the iParcelBox Local API
Home-page: https://github.com/gadget-man/iparcelboxpy
Author: iParcelBox Ltd
Author-email: support@iparcelbox.com
License: MIT
Project-URL: Bug Tracker, https://github.com/gadget-man/iparcelboxpy/issues
Platform: Cross Platform
License-File: LICENSE.txt
Requires-Dist: requests
